dexcomm.cpython-313-x86_64-linux-gnu.so
dexcomm.pyi
dexcomm/py.typed
dexcomm.build/.gitignore
dexcomm-0.1.17.dist-info/METADATA
dexcomm-0.1.17.dist-info/WHEEL
dexcomm-0.1.17.dist-info/top_level.txt
dexcomm-0.1.17.dist-info/RECORD
dexcomm-0.1.17.dist-info/licenses/LICENSE
