Metadata-Version: 2.4
Name: dexcomm
Version: 0.1.17
Summary: Communication library using Zenoh with ROS-like functionality
Author-email: Dexmate <contact@dexmate.ai>
Maintainer-email: Dexmate <contact@dexmate.ai>
License: Dual licensed: AGPL-3.0 and Commercial
Project-URL: Homepage, https://github.com/dexmate/dexcomm
Project-URL: Documentation, https://github.com/dexmate/dexcomm#readme
Project-URL: Repository, https://github.com/dexmate/dexcomm.git
Project-URL: Issues, https://github.com/dexmate/dexcomm/issues
Keywords: communication,robotics,AI
Classifier: Development Status :: 4 - Beta
Classifier: Intended Audience :: Developers
Classifier: Intended Audience :: Science/Research
Classifier: License :: OSI Approved :: GNU Affero General Public License v3
Classifier: License :: Other/Proprietary License
Classifier: Operating System :: POSIX :: Linux
Classifier: Operating System :: MacOS :: MacOS X
Classifier: Operating System :: Microsoft :: Windows
Classifier: Programming Language :: Python :: 3
Classifier: Programming Language :: Python :: 3.10
Classifier: Programming Language :: Python :: 3.11
Classifier: Programming Language :: Python :: 3.12
Classifier: Programming Language :: Python :: 3.13
Classifier: Topic :: Scientific/Engineering
Classifier: Topic :: Software Development :: Libraries :: Python Modules
Classifier: Topic :: System :: Distributed Computing
Classifier: Topic :: System :: Networking
Requires-Python: >=3.10
License-File: LICENSE
Requires-Dist: eclipse-zenoh>=1.5.0
Requires-Dist: numpy>=1.20.0
Requires-Dist: loguru>=0.6.0
Requires-Dist: protobuf>=6.32.1
Requires-Dist: zstandard>=0.25.0
Provides-Extra: image
Requires-Dist: opencv-python>=4.5.0; extra == "image"
Provides-Extra: fast
Requires-Dist: PyTurboJPEG>=1.6.0; extra == "fast"
Provides-Extra: yaml
Requires-Dist: PyYAML>=6.0; extra == "yaml"
Provides-Extra: dev
Requires-Dist: pytest>=7.0.0; extra == "dev"
Requires-Dist: pytest-cov>=4.0.0; extra == "dev"
Requires-Dist: pytest-asyncio>=0.21.0; extra == "dev"
Requires-Dist: pytest-timeout>=2.1.0; extra == "dev"
Requires-Dist: black>=23.0.0; extra == "dev"
Requires-Dist: ruff>=0.1.0; extra == "dev"
Requires-Dist: mypy>=1.0.0; extra == "dev"
Requires-Dist: types-protobuf>=4.0.0; extra == "dev"
Requires-Dist: Pillow>=9.0.0; extra == "dev"
Provides-Extra: all
Requires-Dist: dexcomm[fast,image,yaml]; extra == "all"
Dynamic: license-file
